qvvikolib/__init__.py
qvvikolib/demo.py
qvvikolib/multiprocessing.py
qvvikolib-0.0.7.dist-info/LICENSE
qvvikolib-0.0.7.dist-info/METADATA
qvvikolib-0.0.7.dist-info/WHEEL
qvvikolib-0.0.7.dist-info/top_level.txt
qvvikolib-0.0.7.dist-info/RECORD
