Metadata-Version: 2.1
Name: qvvikolib
Version: 0.0.7
Summary: Utils by qvviko
Home-page: https://github.com/qvviko/qvvikolib
Author: Vladislav Savchuk
Author-email: qvviko@gmail.com
License: MIT
Platform: UNKNOWN
